odoo10_addon_report_xlsx-10.0.1.1.1-nspkg.pth
odoo/addons/report_xlsx/README.rst
odoo/addons/report_xlsx/__init__.py
odoo/addons/report_xlsx/__manifest__.py
odoo/addons/report_xlsx/i18n/de.po
odoo/addons/report_xlsx/i18n/es.po
odoo/addons/report_xlsx/i18n/fr.po
odoo/addons/report_xlsx/i18n/hr.po
odoo/addons/report_xlsx/i18n/hr_HR.po
odoo/addons/report_xlsx/i18n/it.po
odoo/addons/report_xlsx/i18n/nl_NL.po
odoo/addons/report_xlsx/i18n/pt_PT.po
odoo/addons/report_xlsx/i18n/report_xlsx.pot
odoo/addons/report_xlsx/i18n/tr.po
odoo/addons/report_xlsx/models/__init__.py
odoo/addons/report_xlsx/models/header_footer.py
odoo/addons/report_xlsx/models/ir_report.py
odoo/addons/report_xlsx/report/__init__.py
odoo/addons/report_xlsx/report/report_xlsx.py
odoo/addons/report_xlsx/security/ir.model.access.csv
odoo/addons/report_xlsx/static/description/icon.png
odoo/addons/report_xlsx/tests/__init__.py
odoo/addons/report_xlsx/tests/test_header_footer.py
odoo/addons/report_xlsx/views/header_footer.xml
odoo/addons/report_xlsx/views/ir_report.xml
odoo10_addon_report_xlsx-10.0.1.1.1.dist-info/METADATA
odoo10_addon_report_xlsx-10.0.1.1.1.dist-info/WHEEL
odoo10_addon_report_xlsx-10.0.1.1.1.dist-info/namespace_packages.txt
odoo10_addon_report_xlsx-10.0.1.1.1.dist-info/top_level.txt
odoo10_addon_report_xlsx-10.0.1.1.1.dist-info/RECORD
